enum_extend/__init__.py
enum_extend/__main__.py
enum_extend-0.1.1.dist-info/LICENSE
enum_extend-0.1.1.dist-info/METADATA
enum_extend-0.1.1.dist-info/WHEEL
enum_extend-0.1.1.dist-info/top_level.txt
enum_extend-0.1.1.dist-info/RECORD
