Metadata-Version: 2.1
Name: enum-extend
Version: 0.1.1
Summary: Enum base classes that support enum comparsion and auto numbering with doc strings
Home-page: https://github.com/Amourspirit/python-enum-extend
Author: :Barry-Thomas-Paul: Moss
Author-email: bigbytetech@gmail.com
License: MIT
Keywords: python,enum,autoenum,compare-enum,enum-compare,enum-docstring
Platform: UNKNOWN
Classifier: License :: OSI Approved :: MIT License
Classifier: Programming Language :: Python :: 3
Classifier: Programming Language :: Python :: 3.4
Classifier: Programming Language :: Python :: 3.5
Classifier: Programming Language :: Python :: 3.6
Classifier: Programming Language :: Python :: 3.7
Classifier: Programming Language :: Python :: 3.8
Classifier: Programming Language :: Python :: 3.9
Requires-Python: >=3.4.0
License-File: LICENSE
